conan_explorer/__init__.py
conan_explorer/__main__.py
conan_explorer/app/__init__.py
conan_explorer/app/logger.py
conan_explorer/app/system.py
conan_explorer/app/typing.py
conan_explorer/app/base_ui/__init__.py
conan_explorer/app/base_ui/crash.py
conan_explorer/app/base_ui/loading.py
conan_explorer/app/base_ui/theming.py
conan_explorer/assets/config_schema.json
conan_explorer/assets/launch.bat.in
conan_explorer/assets/launch.sh.in
conan_explorer/assets/font/NotoSans-Regular.ttf
conan_explorer/assets/font/NotoSansMono.ttf
conan_explorer/assets/icons/conan.png
conan_explorer/assets/icons/icon.ico
conan_explorer/assets/icons/global/android.svg
conan_explorer/assets/icons/global/conan_logo.svg
conan_explorer/assets/icons/global/conan_settings.svg
conan_explorer/assets/icons/global/grid.svg
conan_explorer/assets/icons/global/linux.svg
conan_explorer/assets/icons/global/mac_os.svg
conan_explorer/assets/icons/global/package.svg
conan_explorer/assets/icons/global/package_explorer.svg
conan_explorer/assets/icons/global/package_orig.svg
conan_explorer/assets/icons/global/search_packages.svg
conan_explorer/assets/icons/global/windows.svg
conan_explorer/assets/icons/material/about.svg
conan_explorer/assets/icons/material/add_link.svg
conan_explorer/assets/icons/material/app.svg
conan_explorer/assets/icons/material/arrow_down.svg
conan_explorer/assets/icons/material/arrow_up.svg
conan_explorer/assets/icons/material/back.svg
conan_explorer/assets/icons/material/bar_chart.svg
conan_explorer/assets/icons/material/check_box_checked.svg
conan_explorer/assets/icons/material/check_box_empty.svg
conan_explorer/assets/icons/material/cleanup.svg
conan_explorer/assets/icons/material/clear_all.svg
conan_explorer/assets/icons/material/close.svg
conan_explorer/assets/icons/material/close_lgr.svg
conan_explorer/assets/icons/material/close_white_lgr.svg
conan_explorer/assets/icons/material/cmd.svg
conan_explorer/assets/icons/material/collapse_all.svg
conan_explorer-2.4.2.dist-info/licenses/LICENSE
conan_explorer-2.4.2.dist-info/METADATA
conan_explorer-2.4.2.dist-info/WHEEL
conan_explorer-2.4.2.dist-info/entry_points.txt
conan_explorer-2.4.2.dist-info/top_level.txt
conan_explorer-2.4.2.dist-info/RECORD
