Metadata-Version: 2.4
Name: conan-explorer
Version: 2.4.2
Summary: Package Explorer and App Launcher for Conan
Author: Péter Gosztolya and Contributors
License: GNU LESSER GENERAL PUBLIC LICENSE
Project-URL: repository, https://github.com/goszpeti/conan_explorer
Project-URL: issues, https://github.com/goszpeti/conan_explorer/issues
Keywords: conan,gui
Classifier: License :: OSI Approved :: GNU Lesser General Public License v3 (LGPLv3)
Classifier: Programming Language :: Python
Classifier: Programming Language :: Python :: 3
Classifier: Programming Language :: Python :: 3.8
Classifier: Programming Language :: Python :: 3.9
Classifier: Programming Language :: Python :: 3.10
Classifier: Programming Language :: Python :: 3.11
Classifier: Programming Language :: Python :: 3.12
Classifier: Programming Language :: Python :: Implementation :: CPython
Classifier: Environment :: X11 Applications :: Qt
Classifier: Environment :: Win32 (MS Windows)
Requires-Python: >=3.8
License-File: LICENSE
Requires-Dist: conan-unified-api<3.0.0,>=2.15.0
Requires-Dist: PySide6-Essentials>=6.4.3
Requires-Dist: jsonschema<5,>=3.2.0
Requires-Dist: dictdiffer==0.9.0
Requires-Dist: contextlib-chdir==1.0.2; python_version < "3.11"
Requires-Dist: typing-extensions<5,>=4.2.0
Requires-Dist: packaging
Provides-Extra: dev
Requires-Dist: rope; extra == "dev"
Requires-Dist: debugpy; extra == "dev"
Provides-Extra: test
Requires-Dist: pytest==8.3.3; extra == "test"
Requires-Dist: pytest-cov==5.0.0; extra == "test"
Requires-Dist: pytest-mock==3.14.0; extra == "test"
Requires-Dist: pytest-qt==4.4.0; extra == "test"
Requires-Dist: psutil==6.1.1; extra == "test"
Requires-Dist: pytest-check==2.4.1; extra == "test"
Requires-Dist: pywin32; sys_platform == "win32" and extra == "test"
Dynamic: license-file
